cdk8s_cli/__init__.py
cdk8s_cli/cdk8s_cli.py
cdk8s_cli/functions/internals/errors.py
cdk8s_cli/functions/internals/parse_args.py
cdk8s_cli/functions/internals/printing.py
cdk8s_cli/functions/internals/synth.py
cdk8s_cli/functions/reads/diff.py
cdk8s_cli/functions/reads/get_resource.py
cdk8s_cli/functions/reads/get_resources_ready_status.py
cdk8s_cli/functions/reads/list.py
cdk8s_cli/functions/reads/validate.py
cdk8s_cli/functions/writes/apply.py
cdk8s_cli/functions/writes/delete.py
cdk8s_cli-0.1.0a7.dist-info/METADATA
cdk8s_cli-0.1.0a7.dist-info/WHEEL
cdk8s_cli-0.1.0a7.dist-info/RECORD
