Metadata-Version: 2.3
Name: cdk8s_cli
Version: 0.1.0a7
Summary: A simple CLI for cdk8s
Author: Matthew Cane
Author-email: matthew.cane0@gmail.com
Requires-Python: >=3.12,<4.0
Classifier: Programming Language :: Python :: 3
Classifier: Programming Language :: Python :: 3.12
Classifier: Programming Language :: Python :: 3.13
Requires-Dist: cdk8s-plus-31 (>=2.1.2,<3.0.0)
Requires-Dist: dictdiffer (>=0.9.0,<0.10.0)
Requires-Dist: kubernetes (>=32.0.0,<33.0.0)
Requires-Dist: more-itertools (>=10.5.0,<11.0.0)
Requires-Dist: pyyaml (>=6.0.2,<7.0.0)
Requires-Dist: rich (>=13.9.1,<14.0.0)
